tut1/project_1/project_1.srcs/sources_1/new/full_adder.v
`timescale 1ns / 1ps
//////////////////////////////////////////////////////////////////////////////////
// Company: 
// Engineer: 
// 
// Create Date: 02/28/2024 02:21:37 PM
// Design Name: 
// Module Name: full_adder
// Project Name: 
// Target Devices: 
// Tool Versions: 
// Description: 
// 
// Dependencies: 
// 
// Revision:
// Revision 0.01 - File Created
// Additional Comments:
// 
//////////////////////////////////////////////////////////////////////////////////


module full_adder(A,B,Cin,S,Cout);
    input A,B,Cin;
    output S,Cout;
    
    wire S_wire0, S_wire1, S_wire2, S_wire3;
    wire not_A,not_B,not_Cin;
    
    not(not_A,A);
    not(not_B,B);
    not(not_Cin,Cin);
    
    and(S_wire0,not_A,not_B,Cin);
    and(S_wire1,not_A,B,not_Cin);
    and(S_wire2,A,not_B,not_Cin);
    and(S_wire3,A,B,Cin);
    or(S,S_wire0, S_wire1, S_wire2, S_wire3);
    
    wire C_wire0,C_wire1, C_wire2;
    and(C_wire0,A,B);
    and(C_wire1,B,Cin);
    and(C_wire2,A,Cin);
    or(Cout,C_wire0,C_wire1,C_wire2);
 


endmodule

tut1/project_1/project_1.srcs/sim_1/new/full_adder_tb.v
`timescale 1ns / 1ps
//////////////////////////////////////////////////////////////////////////////////
// Company: 
// Engineer: 
// 
// Create Date: 02/28/2024 02:23:03 PM
// Design Name: 
// Module Name: full_adder_tb
// Project Name: 
// Target Devices: 
// Tool Versions: 
// Description: 
// 
// Dependencies: 
// 
// Revision:
// Revision 0.01 - File Created
// Additional Comments:
// 
//////////////////////////////////////////////////////////////////////////////////


module full_adder_tb();

    reg tb_A, tb_B, tb_Cin;
    wire tb_S, tb_Cout;
    
    full_adder myFull_adder(
        .A  (tb_A),
        .B  (tb_B),
        .Cin  (tb_Cin),
        .S  (tb_S),
        .Cout  (tb_Cout)
    );
    initial
    
    begin
    $dumpvars;
    $monitor("%b+%b+%b= Cout = %b S=%b",tb_A,tb_B,tb_Cin,tb_Cout,tb_S);
        #5 tb_A=0;tb_B=0;tb_Cin=0;
        #5 tb_A=0;tb_B=0;tb_Cin=1;
        #5 tb_A=0;tb_B=1;tb_Cin=0;
        #5 tb_A=0;tb_B=1;tb_Cin=1;
        #5 tb_A=1;tb_B=0;tb_Cin=0;
        #5 tb_A=1;tb_B=0;tb_Cin=1;
        #5 tb_A=1;tb_B=1;tb_Cin=0;
        #5 tb_A=1;tb_B=1;tb_Cin=1;
        #5 $finish;
    

end 
endmodule

tut1/project_1/project_1.sim/sim_1/behav/xsim/dump.vcd
$date
   Wed Feb 28 15:08:24 2024
$end

$version
  2023.2
$end

$timescale
  1ps
$end

$scope module full_adder_tb $end
$var reg 1 ! tb_A $end
$var reg 1 " tb_B $end
$var reg 1 # tb_Cin $end
$var wire 1 $ tb_S $end
$var wire 1 % tb_Cout $end
$scope module myFull_adder $end
$var wire 1 & A $end
$var wire 1 ' B $end
$var wire 1 ( Cin $end
$var wire 1 $ S $end
$var wire 1 % Cout $end
$var wire 1 ) S_wire0 $end
$var wire 1 * S_wire1 $end
$var wire 1 + S_wire2 $end
$var wire 1 , S_wire3 $end
$var wire 1 - not_A $end
$var wire 1 . not_B $end
$var wire 1 / not_Cin $end
$var wire 1 0 C_wire0 $end
$var wire 1 1 C_wire1 $end
$var wire 1 2 C_wire2 $end
$upscope $end
$upscope $end
$enddefinitions $end

#0
$dumpvars
x!
x"
x#
x$
x%
x&
x'
x(
x)
x*
x+
x,
x-
x.
x/
x0
x1
x2
$end

#5000
0!
0"
0#
0$
0%
0&
0'
0(
0)
0*
0+
0,
1-
1.
1/
00
01
02

#10000
1#
1$
1(
1)
0/

#15000
1"
0#
1'
0(
0)
1*
0.
1/

#20000
1#
0$
1%
1(
0*
0/
11

#25000
1!
0"
0#
1$
0%
1&
0'
0(
1+
0-
1.
1/
01

#30000
1#
0$
1%
1(
0+
0/
12

#35000
1"
0#
1'
0(
0.
1/
10
02

#40000
1#
1$
1(
1,
0/
11
12
