tut2/task3/project_1/project_1.srcs/sources_1/new/circuit.v
`timescale 1ns / 1ps
//////////////////////////////////////////////////////////////////////////////////
// Company: 
// Engineer: 
// 
// Create Date: 02/29/2024 02:58:07 PM
// Design Name: 
// Module Name: circuit
// Project Name: 
// Target Devices: 
// Tool Versions: 
// Description: 
// 
// Dependencies: 
// 
// Revision:
// Revision 0.01 - File Created
// Additional Comments:
// 
//////////////////////////////////////////////////////////////////////////////////


module circuit(A,B,C,D,F);
    output F;
    input A,B,C,D;
    
    //assign F=((~A&~B&~C&~D) | (A&D) | (B&C&~D) | (~B&C&D));
    
    assign F=(~A|B)&(~B|C|~D)&(~A|D);
endmodule

tut2/task3/project_1/project_1.srcs/sim_1/new/testbench.v
`timescale 1ns / 1ps
//////////////////////////////////////////////////////////////////////////////////
// Company: 
// Engineer: 
// 
// Create Date: 02/29/2024 02:58:25 PM
// Design Name: 
// Module Name: testbench
// Project Name: 
// Target Devices: 
// Tool Versions: 
// Description: 
// 
// Dependencies: 
// 
// Revision:
// Revision 0.01 - File Created
// Additional Comments:
// 
//////////////////////////////////////////////////////////////////////////////////


module testbench();

reg A,B,C,D;
wire F;

circuit SOP1(A,B,C,D,F);

initial
begin
    $dumpvars;
    $monitor(A,B,C,D,F);
    for(integer i=0; i<16; i=i+1)
        begin
            #5 {A,B,C,D}=i;
        end
        
    #5 $finish;
end

endmodule

tut2/task3/project_1/project_1.sim/sim_1/behav/xsim/dump.vcd
$date
   Thu Feb 29 16:17:58 2024
$end

$version
  2023.2
$end

$timescale
  1ps
$end

$scope module testbench $end
$var reg 1 ! A $end
$var reg 1 " B $end
$var reg 1 # C $end
$var reg 1 $ D $end
$var wire 1 % F $end
$scope module SOP1 $end
$var wire 1 % F $end
$var wire 1 & A $end
$var wire 1 ' B $end
$var wire 1 ( C $end
$var wire 1 ) D $end
$upscope $end
$scope begin Block34_1 $end
$var integer 32 * i [31:0] $end
$upscope $end
$upscope $end
$enddefinitions $end

#0
$dumpvars
x!
x"
x#
x$
x%
x&
x'
x(
x)
b0 *
$end

#5000
0!
0"
0#
0$
1%
0&
0'
0(
0)
b1 *

#10000
1$
1)
b10 *

#15000
1#
0$
1(
0)
b11 *

#20000
1$
1)
b100 *

#25000
1"
0#
0$
1'
0(
0)
b101 *

#30000
1$
0%
1)
b110 *

#35000
1#
0$
1%
1(
0)
b111 *

#40000
1$
1)
b1000 *

#45000
1!
0"
0#
0$
0%
1&
0'
0(
0)
b1001 *

#50000
1$
1)
b1010 *

#55000
1#
0$
1(
0)
b1011 *

#60000
1$
1)
b1100 *

#65000
1"
0#
0$
1'
0(
0)
b1101 *

#70000
1$
1)
b1110 *

#75000
1#
0$
1(
0)
b1111 *
